[{"data": [{"out_path": "C:\\Users\\soham\\Desktop\\Soham\\Projects\\OSO\\echodataflow\\docs\\source\\local\\echodataflow-output\\echodataflow_compute_TS\\2017\\Summer2017-D20170615-T190214_TS.zarr", "transect": "2017", "file_name": "Summer2017-D20170615-T190214_TS.zarr", "error": false}, {"out_path": "C:\\Users\\soham\\Desktop\\Soham\\Projects\\OSO\\echodataflow\\docs\\source\\local\\echodataflow-output\\echodataflow_compute_TS\\2017\\Summer2017-D20170615-T190843_TS.zarr", "transect": "2017", "file_name": "Summer2017-D20170615-T190843_TS.zarr", "error": false}, {"out_path": "C:\\Users\\soham\\Desktop\\Soham\\Projects\\OSO\\echodataflow\\docs\\source\\local\\echodataflow-output\\echodataflow_compute_TS\\2017\\Summer2017-D20170615-T212409_TS.zarr", "transect": "2017", "file_name": "Summer2017-D20170615-T212409_TS.zarr", "error": false}, {"out_path": "C:\\Users\\soham\\Desktop\\Soham\\Projects\\OSO\\echodataflow\\docs\\source\\local\\echodataflow-output\\echodataflow_compute_TS\\2017\\Summer2017-D20170615-T212933_TS.zarr", "transect": "2017", "file_name": "Summer2017-D20170615-T212933_TS.zarr", "error": false}, {"out_path": "C:\\Users\\soham\\Desktop\\Soham\\Projects\\OSO\\echodataflow\\docs\\source\\local\\echodataflow-output\\echodataflow_compute_TS\\2017\\Summer2017-D20170615-T213153_TS.zarr", "transect": "2017", "file_name": "Summer2017-D20170615-T213153_TS.zarr", "error": false}, {"out_path": "C:\\Users\\soham\\Desktop\\Soham\\Projects\\OSO\\echodataflow\\docs\\source\\local\\echodataflow-output\\echodataflow_compute_TS\\2017\\Summer2017-D20170615-T214606_TS.zarr", "transect": "2017", "file_name": "Summer2017-D20170615-T214606_TS.zarr", "error": false}, {"out_path": "C:\\Users\\soham\\Desktop\\Soham\\Projects\\OSO\\echodataflow\\docs\\source\\local\\echodataflow-output\\echodataflow_compute_TS\\2017\\Summer2017-D20170615-T214712_TS.zarr", "transect": "2017", "file_name": "Summer2017-D20170615-T214712_TS.zarr", "error": false}, {"out_path": "C:\\Users\\soham\\Desktop\\Soham\\Projects\\OSO\\echodataflow\\docs\\source\\local\\echodataflow-output\\echodataflow_compute_TS\\2017\\Summer2017-D20170615-T214734_TS.zarr", "transect": "2017", "file_name": "Summer2017-D20170615-T214734_TS.zarr", "error": false}, {"out_path": "C:\\Users\\soham\\Desktop\\Soham\\Projects\\OSO\\echodataflow\\docs\\source\\local\\echodataflow-output\\echodataflow_compute_TS\\2017\\Summer2017-D20170619-T225736_TS.zarr", "transect": "2017", "file_name": "Summer2017-D20170619-T225736_TS.zarr", "error": false}, {"out_path": "C:\\Users\\soham\\Desktop\\Soham\\Projects\\OSO\\echodataflow\\docs\\source\\local\\echodataflow-output\\echodataflow_compute_TS\\2017\\Summer2017-D20170619-T231647_TS.zarr", "transect": "2017", "file_name": "Summer2017-D20170619-T231647_TS.zarr", "error": false}, {"out_path": "C:\\Users\\soham\\Desktop\\Soham\\Projects\\OSO\\echodataflow\\docs\\source\\local\\echodataflow-output\\echodataflow_compute_TS\\2017\\Summer2017-D20170619-T233922_TS.zarr", "transect": "2017", "file_name": "Summer2017-D20170619-T233922_TS.zarr", "error": false}, {"out_path": "C:\\Users\\soham\\Desktop\\Soham\\Projects\\OSO\\echodataflow\\docs\\source\\local\\echodataflow-output\\echodataflow_compute_TS\\2017\\Summer2017-D20170620-T002659_TS.zarr", "transect": "2017", "file_name": "Summer2017-D20170620-T002659_TS.zarr", "error": false}, {"out_path": "C:\\Users\\soham\\Desktop\\Soham\\Projects\\OSO\\echodataflow\\docs\\source\\local\\echodataflow-output\\echodataflow_compute_TS\\2017\\Summer2017-D20170620-T005939_TS.zarr", "transect": "2017", "file_name": "Summer2017-D20170620-T005939_TS.zarr", "error": false}, {"out_path": "C:\\Users\\soham\\Desktop\\Soham\\Projects\\OSO\\echodataflow\\docs\\source\\local\\echodataflow-output\\echodataflow_compute_TS\\2017\\Summer2017-D20170620-T011027_TS.zarr", "transect": "2017", "file_name": "Summer2017-D20170620-T011027_TS.zarr", "error": false}, {"out_path": "C:\\Users\\soham\\Desktop\\Soham\\Projects\\OSO\\echodataflow\\docs\\source\\local\\echodataflow-output\\echodataflow_compute_TS\\2017\\Summer2017-D20170620-T014302_TS.zarr", "transect": "2017", "file_name": "Summer2017-D20170620-T014302_TS.zarr", "error": false}, {"out_path": "C:\\Users\\soham\\Desktop\\Soham\\Projects\\OSO\\echodataflow\\docs\\source\\local\\echodataflow-output\\echodataflow_compute_TS\\2017\\Summer2017-D20170620-T021537_TS.zarr", "transect": "2017", "file_name": "Summer2017-D20170620-T021537_TS.zarr", "error": false}, {"out_path": "C:\\Users\\soham\\Desktop\\Soham\\Projects\\OSO\\echodataflow\\docs\\source\\local\\echodataflow-output\\echodataflow_compute_TS\\2017\\Summer2017-D20170620-T024811_TS.zarr", "transect": "2017", "file_name": "Summer2017-D20170620-T024811_TS.zarr", "error": false}, {"out_path": "C:\\Users\\soham\\Desktop\\Soham\\Projects\\OSO\\echodataflow\\docs\\source\\local\\echodataflow-output\\echodataflow_compute_TS\\2017\\Summer2017-D20170620-T032047_TS.zarr", "transect": "2017", "file_name": "Summer2017-D20170620-T032047_TS.zarr", "error": false}, {"out_path": "C:\\Users\\soham\\Desktop\\Soham\\Projects\\OSO\\echodataflow\\docs\\source\\local\\echodataflow-output\\echodataflow_compute_TS\\2017\\Summer2017-D20170620-T043221_TS.zarr", "transect": "2017", "file_name": "Summer2017-D20170620-T043221_TS.zarr", "error": false}, {"out_path": "C:\\Users\\soham\\Desktop\\Soham\\Projects\\OSO\\echodataflow\\docs\\source\\local\\echodataflow-output\\echodataflow_compute_TS\\2017\\Summer2017-D20170620-T061742_TS.zarr", "transect": "2017", "file_name": "Summer2017-D20170620-T061742_TS.zarr", "error": false}], "passing_params": {}}]